{"assets":{"images":[{"name":"items-kimi","path":"/items/kimi.png","frameWidth":"32","frameHeight":"32","loaded":true}]},"objects":{"type":"LR.Entity.Group","name":"kimis","id":200,"x":0,"y":0,"scaleX":1,"scaleY":1,"angle":0,"width":136.00000381469727,"height":104.00000095367432,"prefab":{"name":"kimis","path":"/kimis.json"},"visible":true,"alpha":1,"behaviours":[],"children":[{"type":"LR.Entity.Sprite","name":"kimi0","id":201,"x":138.99999618530273,"y":151.00000381469727,"scaleX":0.625,"scaleY":0.625,"angle":0,"anchor":{"x":0.5,"y":0.5},"width":20,"height":20,"visible":true,"alpha":1,"key":"items-kimi","frame":0,"tint":16777215,"anims":{"idle":{"frames":[0,0,0,0,0,0,0,0,0,0,0,0,0,1,2],"loop":true,"speed":4}},"autoPlayAnim":"idle","layer":"default","body":{"motion":"DYNAMIC","enabled":true,"angle":0,"gravity":1,"mass":1,"debug":false,"shapes":[{"x":0,"y":-5,"width":32,"height":25,"rotation":0,"name":"mainShape","id":0,"sensor":false}]},"behaviours":[{"name":"Kimi","params":{"id":0},"path":"/items/kimi.js","$$hashKey":"07I"}]},{"type":"LR.Entity.Sprite","name":"kimi1","id":202,"x":205,"y":115,"scaleX":0.625,"scaleY":0.625,"angle":0,"anchor":{"x":0.5,"y":0.5},"width":20,"height":20,"visible":true,"alpha":1,"key":"items-kimi","frame":3,"tint":16777215,"anims":{"idle":{"frames":[3,4,5,4],"loop":true,"speed":16}},"autoPlayAnim":"idle","layer":"default","body":{"motion":"DYNAMIC","enabled":true,"angle":0,"gravity":1,"mass":1,"debug":false,"shapes":[{"x":0,"y":-5,"width":32,"height":25,"rotation":0,"name":"mainShape","id":0,"sensor":false}]},"behaviours":[{"name":"Kimi","params":{"id":1},"path":"/items/kimi.js","$$hashKey":"07I"}]},{"type":"LR.Entity.Sprite","name":"kimi2","id":203,"x":255,"y":67.00000286102295,"scaleX":0.625,"scaleY":0.625,"angle":0,"anchor":{"x":0.5,"y":0.5},"width":20,"height":20,"visible":true,"alpha":1,"key":"items-kimi","frame":6,"tint":16777215,"anims":{"idle":{"frames":[6,6,6,6,6,6,6,6,6,6,6,6,6,6,6,6,6,6,7,8],"loop":true,"speed":6}},"autoPlayAnim":"idle","layer":"default","body":{"motion":"DYNAMIC","enabled":true,"angle":0,"gravity":1,"mass":1,"debug":false,"shapes":[{"x":0,"y":-5,"width":32,"height":25,"rotation":0,"name":"mainShape","id":0,"sensor":false}]},"behaviours":[{"name":"Kimi","params":{"id":2},"path":"/items/kimi.js","$$hashKey":"07I"}]}]}}