{"assets":{"images":[{"name":"HD-dusk_sky_512x512","path":"/HD/dusk_sky_512x512.jpg","frameWidth":512,"frameHeight":512,"loaded":true},{"name":"enemies-smoke","path":"/enemies/smoke.png","frameWidth":"48","frameHeight":"48","loaded":true},{"name":"decor-brownrock-ground","path":"/decor/brownrock/ground.png","frameWidth":"64","frameHeight":"32","loaded":true},{"name":"decor-stone-ground","path":"/decor/stone/ground.png","frameWidth":"64","frameHeight":"32","loaded":true},{"name":"decor-plant-grass_middle_128x64","path":"/decor/plant/grass_middle_128x64.png","frameWidth":128,"frameHeight":64,"loaded":true},{"name":"items-bird_hook","path":"/items/bird_hook.png","frameWidth":"64","frameHeight":"64","loaded":true},{"name":"items-bonuses","path":"/items/bonuses.png","frameWidth":"64","frameHeight":"64","loaded":true},{"name":"decor-stone-mini_block","path":"/decor/stone/mini_block.png","frameWidth":"32","frameHeight":"32","loaded":true},{"name":"komo","path":"/komo.png","frameWidth":"64","frameHeight":"64","loaded":true},{"name":"komo_hair","path":"/komo_hair.png","frameWidth":"64","frameHeight":"64","loaded":true},{"name":"acolyte","path":"/acolyte.png","frameWidth":"32","frameHeight":"32","loaded":true},{"name":"enemies-francis-eye","path":"/enemies/francis/eye.png","frameWidth":"64","frameHeight":"64","loaded":true},{"name":"items-egg","path":"/items/egg.png","frameWidth":"32","frameHeight":"32","loaded":true},{"name":"items-life","path":"/items/life.png","frameWidth":"32","frameHeight":"32","loaded":true},{"name":"ui-dir_button","path":"/ui/dir_button.png","frameWidth":"64","frameHeight":"64","loaded":true},{"name":"ui-ingame_buttons_32x32","path":"/ui/ingame_buttons_32x32.png","frameWidth":32,"frameHeight":32,"loaded":true}],"atlases":[{"name":"stone-atlas_stone_1","path":"/stone/atlas_stone_1"},{"name":"francis-atlas","path":"/francis/atlas"}],"sounds":[{"name":"fx-whip_whoosh.wav","path":"/fx/whip_whoosh.wav"},{"name":"fx-jump.wav","path":"/fx/jump.wav"},{"name":"fx-jump2.wav","path":"/fx/jump2.wav"},{"name":"fx-power_drawn.wav","path":"/fx/power_drawn.wav"},{"name":"fx-smoke.wav","path":"/fx/smoke.wav"},{"name":"fx-stomp.wav","path":"/fx/stomp.wav"},{"name":"fx-rock_explode.wav","path":"/fx/rock_explode.wav"}],"behaviours":[{"name":"FallingObject","params":{"direction":1,"hatable":true,"dead":false,"smoke":"#GO_493","repeatTime":-1},"desc":null,"path":"/enemies/falling_object.js","enabled":true,"$$hashKey":"1ZT"},{"name":"FallingObject","params":{"direction":1,"hatable":true,"dead":false,"smoke":"#GO_507","repeatTime":-1},"desc":null,"path":"/enemies/falling_object.js","enabled":true,"$$hashKey":"1ZT"},{"name":"FallingObject","params":{"direction":1,"hatable":true,"dead":false,"smoke":"#GO_510","repeatTime":-1},"desc":null,"path":"/enemies/falling_object.js","enabled":true,"$$hashKey":"1ZT"},{"name":"FallingObject","params":{"direction":1,"hatable":true,"dead":false,"smoke":"#GO_513","repeatTime":-1},"desc":null,"path":"/enemies/falling_object.js","enabled":true,"$$hashKey":"1ZT"},{"name":"Hanger","params":{"distance":28,"hookY":20,"hookX":5},"path":"/other/hanger.js","$$hashKey":"06D","enabled":true},{"name":"LR.Behaviour.ContactNotifier","params":{},"path":"/common/contact_notifier.js","$$hashKey":"06G","enabled":true},{"name":"LR.Behaviour.Trigger","params":{"callbackName":"onActivatePower","messageObject":{"power":"hook"},"interactives":["player"],"activeCountLimit":0},"path":"/common/trigger.js","$$hashKey":"093","enabled":true},{"name":"Player","params":{"acolyte":"#GO_241","hair":"#GO_239","dust1":"#GO_243","dust2":"#GO_244"},"path":"/player.js","$$hashKey":"04Y","enabled":true},{"name":"PlayerHair","params":{"effect":"hair_effect"},"path":"/player_hair.js","$$hashKey":"069","enabled":true},{"name":"Acolyte","params":{},"path":"/other/acolyte.js","$$hashKey":"0SV","enabled":true},{"name":"Francis.MainBody","params":{"tail":"#GO_262","stinger":"#GO_268","legs":"#GO_271","eye":"#GO_261","player":"#GO_238","block_wall":"#GO_484","arm":"#GO_250"},"path":"/enemies/francis/main_body.js","$$hashKey":"0CM","enabled":true},{"name":"Francis.Tail","params":{"stinger":"#GO_268","mainBody":"#GO_255"},"path":"/enemies/francis/tail.js","$$hashKey":"0CM","enabled":true},{"name":"Francis.Stinger","params":{"orb":"#GO_270","stinger":"#GO_269"},"path":"/enemies/francis/stinger.js","$$hashKey":"0CU","enabled":true},{"name":"LR.Behaviour.Trigger","params":{"callbackName":"onHitByRock","messageObject":{},"otherNotified":"#GO_249","activeCountLimit":0},"desc":null,"path":"/common/trigger.js","enabled":true,"$$hashKey":"0O5"},{"name":"Francis.Arm","params":{"boulders":"#GO_490","boulderMe":"#GO_515"},"path":"/enemies/francis/arm.js","$$hashKey":"0CG","enabled":true},{"name":"Francis.Legs","params":{},"desc":null,"path":"/enemies/francis/legs.js","enabled":true,"$$hashKey":"0J5"},{"name":"Francis.Leg","params":{"part1":"#GO_272","part2":"#GO_274"},"desc":null,"path":"/enemies/francis/leg.js","enabled":true,"$$hashKey":"2KL"},{"name":"Francis.Leg","params":{"part1":"#GO_276","part2":"#GO_277"},"desc":null,"path":"/enemies/francis/leg.js","enabled":true,"$$hashKey":"1XH"},{"name":"Francis.Leg","params":{"part1":"#GO_279","part2":"#GO_280"},"desc":null,"path":"/enemies/francis/leg.js","enabled":true,"$$hashKey":"1A8"},{"name":"Francis.Leg","params":{"part1":"#GO_282","part2":"#GO_283"},"desc":null,"path":"/enemies/francis/leg.js","enabled":true,"$$hashKey":"0N4"},{"name":"FallingObject","params":{"direction":1,"hatable":true,"dead":false,"smoke":"#GO_516","repeatTime":-1},"desc":null,"path":"/enemies/falling_object.js","enabled":true,"$$hashKey":"1ZT"},{"name":"UIInGame","params":{"coins":"#GO_286","lives":"#GO_285","quit_button":"#GO_473","mute_button":"#GO_472"},"path":"/ui/ui_ingame.js","$$hashKey":"0A5","enabled":true},{"name":"InputTactile","params":{"leftName":"left_button","rightName":"right_button","player":"#GO_238"},"path":"/ui/input_tactile.js","$$hashKey":"06Q","enabled":true},{"name":"DirectionButton","params":{"direction":"left"},"path":"/ui/direction_button.js","$$hashKey":"06V","enabled":true},{"name":"DirectionButton","params":{"direction":"right"},"path":"/ui/direction_button.js","$$hashKey":"06V","enabled":true},{"name":"QuitButton","params":{},"desc":null,"path":"/ui/quit_button.js","$$hashKey":"0RV","enabled":true},{"name":"MuteButton","params":{},"desc":null,"path":"/ui/mute_button.js","$$hashKey":"0MT","enabled":true},{"name":"LR.Behaviour.Trigger","params":{"callbackName":"launchIntro","messageObject":{},"otherNotified":"#GO_249","activeCountLimit":1,"interactives":["player"]},"desc":null,"path":"/common/trigger.js","enabled":true,"$$hashKey":"0GZ"}],"bitmapFonts":[{"name":"brady_bunch","path":"/brady_bunch.png","pathJson":"/brady_bunch.json","pathData":"/brady_bunch.xml"},{"name":"hungryrex_font1","path":"/hungryrex_font1.png","pathJson":"/hungryrex_font1.json","pathData":"/hungryrex_font1.xml"}]},"objects":{"type":"LR.Entity.Group","name":"__world","x":212,"y":343,"scaleX":1,"scaleY":1,"angle":0,"width":20000,"height":20000,"visible":true,"alpha":1,"behaviours":[],"children":[{"type":"LR.Entity.Group","name":"decor_BG","id":1,"x":0,"y":0,"scaleX":1,"scaleY":1,"angle":0,"width":1053,"height":480,"visible":true,"alpha":1,"behaviours":[],"children":[{"type":"LR.Entity.TileSprite","name":"blue_sky","id":248,"x":247,"y":125,"scaleX":1,"scaleY":1,"angle":0,"anchor":{"x":0.5,"y":0.5},"locked":true,"width":1053,"height":480,"visible":true,"alpha":1,"key":"HD-dusk_sky_512x512","frame":0,"fixedToCamera":true,"tint":16777215,"anims":{},"behaviours":[]}]},{"type":"LR.Entity.Group","name":"Komo_BG","id":2,"x":0,"y":0,"scaleX":1,"scaleY":1,"angle":0,"width":2120.9072217653916,"height":906.0000902704314,"visible":true,"alpha":1,"behaviours":[],"children":[{"type":"LR.Entity.Group","name":"boulders","id":490,"x":0,"y":0,"scaleX":1,"scaleY":1,"angle":0,"width":248.99979972839355,"height":66.99999237060547,"visible":true,"alpha":1,"behaviours":[],"children":[{"type":"LR.Entity.Group","name":"falling_rock_g","id":491,"x":-334,"y":-64,"scaleX":1,"scaleY":1,"angle":0,"width":64,"height":64,"visible":true,"alpha":1,"behaviours":[],"children":[{"type":"LR.Entity.Sprite","name":"rock","id":492,"x":0.00017547607421875,"y":-0.0000057220458984375,"scaleX":1,"scaleY":1,"angle":0,"anchor":{"x":0.5,"y":0.5},"width":64,"height":64,"visible":true,"alpha":1,"key":"stone-atlas_stone_1","frame":1,"frameName":"rock.png","tint":16777215,"anims":{},"layer":"enemy","body":{"motion":"DYNAMIC","enabled":true,"angle":0,"gravity":0,"mass":1,"bindRotation":false,"debug":false,"shapes":[{"x":0,"y":0,"radius":23.000000000000004,"rotation":0,"sensor":true,"name":"mainShape","type":"circle"}]},"behaviours":[{"name":"FallingObject","params":{"direction":1,"hatable":true,"dead":false,"smoke":"#GO_493","repeatTime":-1},"desc":null,"path":"/enemies/falling_object.js","enabled":true,"$$hashKey":"1ZT"}],"sounds":[{"name":"death","key":"fx-rock_explode.wav","autoPlay":false,"loop":true,"volume":1,"is3D":false,"volumeMax3D":1,"distance3D":300,"$$hashKey":"0JW"}]},{"type":"LR.Entity.Sprite","name":"smoke","id":493,"x":0,"y":-4,"scaleX":1,"scaleY":1,"angle":0,"anchor":{"x":0.5,"y":0.5},"width":48,"height":48,"visible":true,"alpha":1,"outOfViewHide":true,"key":"enemies-smoke","frame":0,"tint":16777215,"anims":{"blow":{"frames":[0,1,2,3,4,5,6,7],"loop":false,"speed":20}},"behaviours":[],"sounds":[{"name":"blow","key":"fx-smoke.wav","autoPlay":false,"loop":true,"volume":1,"is3D":false,"volumeMax3D":1,"distance3D":300,"$$hashKey":"0L5"}]}]},{"type":"LR.Entity.Group","name":"falling_rock_1","id":505,"x":-272,"y":-65,"scaleX":1,"scaleY":1,"angle":0,"width":64,"height":64,"visible":true,"alpha":1,"behaviours":[],"children":[{"type":"LR.Entity.Sprite","name":"rock","id":506,"x":-0.0001220703125,"y":0.0000095367431640625,"scaleX":1,"scaleY":1,"angle":0,"anchor":{"x":0.5,"y":0.5},"width":64,"height":64,"visible":true,"alpha":1,"key":"stone-atlas_stone_1","frame":1,"frameName":"rock.png","tint":16777215,"anims":{},"layer":"enemy","body":{"motion":"DYNAMIC","enabled":true,"angle":0,"gravity":0,"mass":1,"bindRotation":false,"debug":false,"shapes":[{"x":0,"y":0,"radius":23.000000000000004,"rotation":0,"sensor":true,"name":"mainShape","type":"circle"}]},"behaviours":[{"name":"FallingObject","params":{"direction":1,"hatable":true,"dead":false,"smoke":"#GO_507","repeatTime":-1},"desc":null,"path":"/enemies/falling_object.js","enabled":true,"$$hashKey":"1ZT"}],"sounds":[{"name":"death","key":"fx-rock_explode.wav","autoPlay":false,"loop":true,"volume":1,"is3D":false,"volumeMax3D":1,"distance3D":300,"$$hashKey":"0JW"}]},{"type":"LR.Entity.Sprite","name":"smoke","id":507,"x":0,"y":-4,"scaleX":1,"scaleY":1,"angle":0,"anchor":{"x":0.5,"y":0.5},"width":48,"height":48,"visible":true,"alpha":1,"outOfViewHide":true,"key":"enemies-smoke","frame":0,"tint":16777215,"anims":{"blow":{"frames":[0,1,2,3,4,5,6,7],"loop":false,"speed":20}},"behaviours":[],"sounds":[{"name":"blow","key":"fx-smoke.wav","autoPlay":false,"loop":true,"volume":1,"is3D":false,"volumeMax3D":1,"distance3D":300,"$$hashKey":"0L5"}]}]},{"type":"LR.Entity.Group","name":"falling_rock_2","id":508,"x":-201,"y":-62,"scaleX":1,"scaleY":1,"angle":0,"width":64,"height":64,"visible":true,"alpha":1,"behaviours":[],"children":[{"type":"LR.Entity.Sprite","name":"rock","id":509,"x":-0.00006103515625,"y":0.0000019073486328125,"scaleX":1,"scaleY":1,"angle":0,"anchor":{"x":0.5,"y":0.5},"width":64,"height":64,"visible":true,"alpha":1,"key":"stone-atlas_stone_1","frame":1,"frameName":"rock.png","tint":16777215,"anims":{},"layer":"enemy","body":{"motion":"DYNAMIC","enabled":true,"angle":0,"gravity":0,"mass":1,"bindRotation":false,"debug":false,"shapes":[{"x":0,"y":0,"radius":23.000000000000004,"rotation":0,"sensor":true,"name":"mainShape","type":"circle"}]},"behaviours":[{"name":"FallingObject","params":{"direction":1,"hatable":true,"dead":false,"smoke":"#GO_510","repeatTime":-1},"desc":null,"path":"/enemies/falling_object.js","enabled":true,"$$hashKey":"1ZT"}],"sounds":[{"name":"death","key":"fx-rock_explode.wav","autoPlay":false,"loop":true,"volume":1,"is3D":false,"volumeMax3D":1,"distance3D":300,"$$hashKey":"0JW"}]},{"type":"LR.Entity.Sprite","name":"smoke","id":510,"x":0,"y":-4,"scaleX":1,"scaleY":1,"angle":0,"anchor":{"x":0.5,"y":0.5},"width":48,"height":48,"visible":true,"alpha":1,"outOfViewHide":true,"key":"enemies-smoke","frame":0,"tint":16777215,"anims":{"blow":{"frames":[0,1,2,3,4,5,6,7],"loop":false,"speed":20}},"behaviours":[],"sounds":[{"name":"blow","key":"fx-smoke.wav","autoPlay":false,"loop":true,"volume":1,"is3D":false,"volumeMax3D":1,"distance3D":300,"$$hashKey":"0L5"}]}]},{"type":"LR.Entity.Group","name":"falling_rock_3","id":511,"x":-149,"y":-62,"scaleX":1,"scaleY":1,"angle":0,"width":64,"height":64,"visible":true,"alpha":1,"behaviours":[],"children":[{"type":"LR.Entity.Sprite","name":"rock","id":512,"x":-0.0000247955322265625,"y":0.0000019073486328125,"scaleX":1,"scaleY":1,"angle":0,"anchor":{"x":0.5,"y":0.5},"width":64,"height":64,"visible":true,"alpha":1,"key":"stone-atlas_stone_1","frame":1,"frameName":"rock.png","tint":16777215,"anims":{},"layer":"enemy","body":{"motion":"DYNAMIC","enabled":true,"angle":0,"gravity":0,"mass":1,"bindRotation":false,"debug":false,"shapes":[{"x":0,"y":0,"radius":23.000000000000004,"rotation":0,"sensor":true,"name":"mainShape","type":"circle"}]},"behaviours":[{"name":"FallingObject","params":{"direction":1,"hatable":true,"dead":false,"smoke":"#GO_513","repeatTime":-1},"desc":null,"path":"/enemies/falling_object.js","enabled":true,"$$hashKey":"1ZT"}],"sounds":[{"name":"death","key":"fx-rock_explode.wav","autoPlay":false,"loop":true,"volume":1,"is3D":false,"volumeMax3D":1,"distance3D":300,"$$hashKey":"0JW"}]},{"type":"LR.Entity.Sprite","name":"smoke","id":513,"x":0,"y":-4,"scaleX":1,"scaleY":1,"angle":0,"anchor":{"x":0.5,"y":0.5},"width":48,"height":48,"visible":true,"alpha":1,"outOfViewHide":true,"key":"enemies-smoke","frame":0,"tint":16777215,"anims":{"blow":{"frames":[0,1,2,3,4,5,6,7],"loop":false,"speed":20}},"behaviours":[],"sounds":[{"name":"blow","key":"fx-smoke.wav","autoPlay":false,"loop":true,"volume":1,"is3D":false,"volumeMax3D":1,"distance3D":300,"$$hashKey":"0L5"}]}]}]},{"type":"LR.Entity.Group","name":"grounds","id":246,"x":0,"y":0,"scaleX":1,"scaleY":1,"angle":0,"width":2120.9072217653916,"height":906.0000902704314,"visible":true,"alpha":1,"behaviours":[],"children":[{"type":"LR.Entity.TileSprite","name":"ground1","id":245,"x":-45.9999942779541,"y":141.0000705718994,"scaleX":1,"scaleY":1,"angle":0,"anchor":{"x":0.5,"y":0.5},"width":1600,"height":32,"visible":true,"alpha":1,"key":"decor-brownrock-ground","frame":0,"tint":16777215,"anims":{},"layer":"ground","body":{"motion":"STATIC","enabled":true,"fixedRotation":true,"angle":0,"gravity":1,"mass":1.7976931348623157e+308,"bindRotation":false,"debug":false,"shapes":[{"x":0,"y":0,"width":1600,"height":32,"rotation":0,"name":"mainShape","type":"rectangle"}]},"behaviours":[]},{"type":"LR.Entity.TileSprite","name":"ground1 (clone)","id":474,"x":-359.9997329711914,"y":-110.66664695739746,"scaleX":1,"scaleY":1,"angle":0,"anchor":{"x":0.5,"y":0.5},"width":576,"height":32,"visible":true,"alpha":1,"key":"decor-brownrock-ground","frame":0,"tint":16777215,"anims":{},"layer":"ground","body":{"motion":"STATIC","enabled":true,"fixedRotation":true,"angle":0,"gravity":1,"mass":1.7976931348623157e+308,"bindRotation":false,"debug":false,"shapes":[{"x":0,"y":0,"width":576,"height":32,"rotation":0,"name":"mainShape","type":"rectangle"}]},"behaviours":[]},{"type":"LR.Entity.TileSprite","name":"ground1 (clone)","id":475,"x":-85.00021934509277,"y":-259.66663360595703,"scaleX":1,"scaleY":1,"angle":0,"anchor":{"x":0.5,"y":0.5},"width":703,"height":32,"visible":true,"alpha":1,"key":"decor-stone-ground","frame":0,"tint":16777215,"anims":{},"layer":"ground","body":{"motion":"STATIC","enabled":true,"fixedRotation":true,"angle":0,"gravity":1,"mass":1.7976931348623157e+308,"bindRotation":false,"debug":false,"shapes":[{"x":0,"y":0,"width":703,"height":32,"rotation":0,"name":"mainShape","type":"rectangle"}]},"behaviours":[]},{"type":"LR.Entity.TileSprite","name":"ceiling","id":476,"x":-41.99997901916504,"y":-560.6666946411133,"scaleX":1,"scaleY":1,"angle":0,"anchor":{"x":0.5,"y":0.5},"width":1843.9186816580332,"height":352.0001271351011,"visible":true,"alpha":1,"key":"decor-stone-ground","frame":0,"tint":16777215,"anims":{},"layer":"ground","body":{"motion":"STATIC","enabled":true,"fixedRotation":true,"angle":0,"gravity":1,"mass":1.7976931348623157e+308,"bindRotation":false,"debug":false,"shapes":[{"x":0,"y":0,"width":1843.9186816580332,"height":352.00012713510114,"rotation":0,"name":"mainShape","type":"rectangle"}]},"behaviours":[]},{"type":"LR.Entity.TileSprite","name":"ground1 (clone)","id":479,"x":-772.9991149902344,"y":-160.66665649414062,"scaleX":1,"scaleY":1,"angle":0,"anchor":{"x":0.5,"y":0.5},"width":256.0000635675506,"height":447.7697317994506,"visible":true,"alpha":1,"key":"decor-stone-ground","frame":0,"tint":16777215,"anims":{},"layer":"ground","body":{"motion":"STATIC","enabled":true,"fixedRotation":true,"angle":0,"gravity":1,"mass":1.7976931348623157e+308,"bindRotation":false,"debug":false,"shapes":[{"x":0,"y":0,"width":256.0000635675506,"height":447.7697317994506,"rotation":0,"name":"mainShape","type":"rectangle"}]},"behaviours":[]},{"type":"LR.Entity.TileSprite","name":"ground1 (clone)","id":480,"x":543.00048828125,"y":-261.6666030883789,"scaleX":1,"scaleY":1,"angle":0,"anchor":{"x":0.5,"y":0.5},"width":383.9281579940078,"height":32,"visible":true,"alpha":1,"key":"decor-stone-ground","frame":0,"tint":16777215,"anims":{},"layer":"ground","body":{"motion":"STATIC","enabled":true,"fixedRotation":true,"angle":0,"gravity":1,"mass":1.7976931348623157e+308,"bindRotation":false,"debug":false,"shapes":[{"x":0,"y":0,"width":959.9280449850289,"height":32,"rotation":0,"name":"mainShape","type":"rectangle"}]},"behaviours":[]},{"type":"LR.Entity.TileSprite","name":"ground1 (clone)","id":481,"x":829.0005493164062,"y":-321.66698455810547,"scaleX":1,"scaleY":1,"angle":0,"anchor":{"x":0.5,"y":0.5},"width":191.92814577208384,"height":127.99999279348279,"visible":true,"alpha":1,"key":"decor-stone-ground","frame":0,"tint":16777215,"anims":{},"layer":"ground","body":{"motion":"STATIC","enabled":true,"fixedRotation":true,"angle":0,"gravity":1,"mass":1.7976931348623157e+308,"bindRotation":false,"debug":false,"shapes":[{"x":0,"y":0,"width":191.92814577208384,"height":127.99999279348279,"rotation":0,"name":"mainShape","type":"rectangle"}]},"behaviours":[]},{"type":"LR.Entity.TileSprite","name":"ground1 (clone)","id":483,"x":-518.8747787475586,"y":-16.666710376739502,"scaleX":1,"scaleY":1,"angle":0,"anchor":{"x":0.5,"y":0.5},"width":256.0000635675506,"height":160,"visible":true,"alpha":1,"key":"decor-stone-ground","frame":0,"tint":16777215,"anims":{},"layer":"ground","body":{"motion":"STATIC","enabled":true,"fixedRotation":true,"angle":0,"gravity":1,"mass":1.7976931348623157e+308,"bindRotation":false,"debug":false,"shapes":[{"x":0,"y":0,"width":256.0000635675506,"height":160,"rotation":0,"name":"mainShape","type":"rectangle"}]},"behaviours":[]},{"type":"LR.Entity.TileSprite","name":"ground1 (clone)","id":489,"x":-231.00006103515625,"y":-63.66663932800293,"scaleX":1,"scaleY":1,"angle":0,"anchor":{"x":0.5,"y":0.5},"width":320.0000232508022,"height":64,"visible":true,"alpha":1,"key":"decor-stone-ground","frame":0,"tint":16777215,"anims":{},"layer":"box","body":{"motion":"STATIC","enabled":true,"fixedRotation":true,"angle":0,"gravity":1,"mass":1.7976931348623157e+308,"bindRotation":false,"debug":false,"shapes":[{"x":0,"y":0,"width":320.00002325080226,"height":66.00000113264332,"rotation":0,"name":"mainShape","type":"rectangle"}]},"behaviours":[]},{"type":"LR.Entity.TileSprite","name":"grass","id":494,"x":-359,"y":-114,"scaleX":1,"scaleY":1,"angle":0,"anchor":{"x":0.5,"y":0.5},"width":574.0076610360187,"height":64,"visible":true,"alpha":1,"key":"decor-plant-grass_middle_128x64","frame":0,"tint":16777215,"anims":{},"behaviours":[]},{"type":"LR.Entity.TileSprite","name":"grass (clone)","id":495,"x":-222,"y":137.33333206176758,"scaleX":1,"scaleY":1,"angle":0,"anchor":{"x":0.5,"y":0.5},"width":1947.885199125887,"height":64,"visible":true,"alpha":1,"key":"decor-plant-grass_middle_128x64","frame":0,"tint":16777215,"anims":{},"behaviours":[]}]},{"type":"LR.Entity.Sprite","name":"bird_hook","id":477,"x":-580.9996795654297,"y":-271.00006103515625,"scaleX":-1,"scaleY":1,"angle":0,"anchor":{"x":0.5,"y":0.5},"width":-64,"height":64,"prefab":{"name":"bird_hook","path":"/bird_hook.json"},"visible":true,"alpha":1,"outOfViewHide":true,"key":"items-bird_hook","frame":0,"tint":16777215,"anims":{"idle":{"frames":[0,1,2,1],"loop":true,"speed":19}},"autoPlayAnim":"idle","layer":"trigger","body":{"motion":"DYNAMIC","enabled":true,"angle":0,"gravity":0,"mass":1.7976931348623157e+308,"bindRotation":false,"debug":false,"shapes":[{"x":1,"y":15,"width":13,"height":36,"rotation":0,"sensor":true,"name":"mainShape","type":"rectangle"}]},"behaviours":[{"name":"Hanger","params":{"distance":28,"hookY":20,"hookX":5},"path":"/other/hanger.js","$$hashKey":"06D","enabled":true},{"name":"LR.Behaviour.ContactNotifier","params":{},"path":"/common/contact_notifier.js","$$hashKey":"06G","enabled":true}],"tweens":{"0":{"name":"tween01","properties":"{\"body.y\":5}","duration":2000,"easing":["Linear","None"],"delay":0,"repeat":-1,"yoyo":true,"relative":true,"$$hashKey":"09F","autoStart":true}},"sounds":[{"name":"release","key":"fx-whip_whoosh.wav","autoPlay":false,"loop":true,"volume":1,"$$hashKey":"0MX"}]},{"type":"LR.Entity.Sprite","name":"bonus_hook","id":478,"x":-355.99952697753906,"y":92.9999828338623,"scaleX":1,"scaleY":1,"angle":0,"anchor":{"x":0.5,"y":0.5},"width":64,"height":64,"prefab":{"name":"bonus_hook","path":"/bonus_hook.json"},"visible":true,"alpha":1,"key":"items-bonuses","frame":2,"tint":16777215,"anims":{},"layer":"trigger","body":{"motion":"DYNAMIC","enabled":true,"angle":0,"gravity":0,"mass":1.7976931348623157e+308,"bindRotation":false,"debug":false,"shapes":[{"x":0,"y":0,"width":40,"height":38,"rotation":0,"sensor":true,"name":"mainShape","type":"rectangle"}]},"behaviours":[{"name":"LR.Behaviour.Trigger","params":{"callbackName":"onActivatePower","messageObject":{"power":"hook"},"interactives":["player"],"activeCountLimit":0},"path":"/common/trigger.js","$$hashKey":"093","enabled":true}],"tweens":{"0":{"name":"tween01","properties":"{\"body.y\":5,\"body.angle\":10}","duration":1300,"easing":["Linear","None"],"delay":0,"$$hashKey":"06M","relative":true,"yoyo":true,"repeat":-1,"autoStart":true}}},{"type":"LR.Entity.Group","name":"wall_g","id":484,"x":-423,"y":93,"scaleX":1,"scaleY":1,"angle":0,"width":144,"height":144,"visible":true,"alpha":1,"behaviours":[],"children":[{"type":"LR.Entity.Sprite","name":"wall_block","id":485,"x":0.00000762939453125,"y":1.0000629425048828,"scaleX":1.8749999998705962,"scaleY":1.8749991145580491,"angle":0,"anchor":{"x":0.5,"y":0.5},"width":59.99999999585908,"height":59.99997166585757,"visible":true,"alpha":1,"key":"decor-stone-mini_block","frame":0,"tint":16777215,"anims":{},"layer":"ground","body":{"motion":"STATIC","enabled":true,"angle":0,"gravity":1,"mass":1.7976931348623157e+308,"bindRotation":false,"debug":false,"shapes":[{"x":0,"y":0,"width":59.9999999958591,"height":59.99997166585757,"rotation":0,"name":"mainShape","type":"rectangle"}]},"behaviours":[]},{"type":"LR.Entity.Sprite","name":"smoke","id":488,"x":0,"y":-8,"scaleX":3,"scaleY":3,"angle":0,"anchor":{"x":0.5,"y":0.5},"width":144,"height":144,"visible":true,"alpha":1,"outOfViewHide":true,"key":"enemies-smoke","frame":0,"tint":16777215,"anims":{"blow":{"frames":[0,1,2,3,4,5,6,7],"loop":false,"speed":20}},"behaviours":[],"sounds":[{"name":"blow","key":"fx-smoke.wav","autoPlay":false,"loop":true,"volume":1,"is3D":false,"volumeMax3D":1,"distance3D":300,"$$hashKey":"0L5"}]}]}]},{"type":"LR.Entity.Group","name":"komoGroup","id":237,"x":0,"y":0,"scaleX":1,"scaleY":1,"angle":0,"width":219.54850000000556,"height":163.00018990039825,"prefab":{"name":"komoGroup","path":"/komoGroup.json"},"visible":true,"alpha":1,"behaviours":[],"children":[{"type":"LR.Entity.Sprite","name":"komo_body","id":238,"x":-500.99849700927734,"y":90.00020027160645,"scaleX":1,"scaleY":1,"angle":0,"anchor":{"x":0.5,"y":0.5},"width":64,"height":64,"visible":true,"alpha":1,"key":"komo","frame":0,"tint":16777215,"anims":{"blink":{"frames":[0,1,2,1,0],"loop":false,"speed":16},"run":{"frames":[6,7,8,7],"loop":true,"speed":22},"jump":{"frames":[3],"loop":true,"speed":60},"fall":{"frames":[4],"loop":true,"speed":60},"push":{"frames":[5],"loop":false,"speed":60},"idle":{"frames":[0],"loop":false,"speed":60}},"layer":"player","body":{"motion":"DYNAMIC","enabled":true,"fixedRotation":true,"angle":0,"gravity":1,"mass":1,"bindRotation":false,"debug":false,"shapes":[{"x":1,"y":-1,"width":23.000000000000004,"height":20,"rotation":0,"name":"mainShape","type":"rectangle"},{"x":1.0000000149011612,"y":12.999999523162842,"width":18,"height":7.000000000000002,"rotation":0,"sensor":true,"name":"feet","type":"rectangle"},{"x":16.00000023841858,"y":0,"width":7.000000000000002,"height":9,"rotation":0,"sensor":true,"name":"right","type":"rectangle"},{"x":-15,"y":0,"width":7.000000000000002,"height":9,"rotation":0,"sensor":true,"name":"left","type":"rectangle"}]},"behaviours":[{"name":"Player","params":{"acolyte":"#GO_241","hair":"#GO_239","dust1":"#GO_243","dust2":"#GO_244"},"path":"/player.js","$$hashKey":"04Y","enabled":true}],"sounds":[{"name":"jump","key":"fx-jump.wav","autoPlay":false,"loop":true,"$$hashKey":"0K3"},{"name":"jump2","key":"fx-jump2.wav","autoPlay":false,"loop":true,"$$hashKey":"0UL"}]},{"type":"LR.Entity.Sprite","name":"komo_hair","id":239,"x":-579.0008926391602,"y":-8.999989628791809,"scaleX":1,"scaleY":1,"angle":0,"anchor":{"x":0.5,"y":0.5},"width":64,"height":64,"visible":true,"alpha":1,"key":"komo_hair","frame":0,"tint":16777215,"anims":{"idle":{"frames":[0],"loop":false,"speed":60},"run":{"frames":[1],"loop":false,"speed":60},"hook":{"frames":[3],"loop":true,"speed":60},"blade":{"frames":[5],"loop":true,"speed":60},"hat":{"frames":[4],"loop":true,"speed":60}},"layer":"player","body":{"motion":"DYNAMIC","enabled":true,"angle":0,"gravity":0,"mass":1,"bindRotation":false,"debug":false,"shapes":[{"x":0,"y":-20,"width":30,"height":30,"rotation":0,"sensor":true,"name":"hook","type":"rectangle"},{"x":15,"y":-8.00000011920929,"width":38,"height":36,"rotation":0,"sensor":true,"name":"blade_right","type":"rectangle"},{"x":-15,"y":-8.00000011920929,"width":38,"height":36,"rotation":0,"sensor":true,"name":"blade_left","type":"rectangle"},{"x":0,"y":-20.999999046325684,"width":52,"height":27,"rotation":0,"sensor":true,"name":"hat","type":"rectangle"}]},"behaviours":[{"name":"PlayerHair","params":{"effect":"hair_effect"},"path":"/player_hair.js","$$hashKey":"069","enabled":true}],"sounds":[{"name":"power","key":"fx-power_drawn.wav","autoPlay":false,"loop":true,"volume":1,"is3D":false,"volumeMax3D":1,"distance3D":300,"$$hashKey":"0WV"}]},{"type":"LR.Entity.Sprite","name":"hair_effect","id":240,"x":-628,"y":13,"scaleX":1,"scaleY":1,"angle":0,"anchor":{"x":0.5,"y":0.5},"width":64,"height":64,"visible":true,"alpha":1,"key":"komo_hair","frame":0,"tint":16777215,"anims":{"blow":{"frames":[6,7,8],"loop":false,"speed":20},"retract":{"frames":[8,7,6],"loop":false,"speed":20}},"behaviours":[]},{"type":"LR.Entity.Sprite","name":"acolyte","id":241,"x":-556,"y":11,"scaleX":0.5,"scaleY":0.5,"angle":0,"anchor":{"x":0.5,"y":0.5},"width":16,"height":16,"visible":true,"alpha":1,"key":"acolyte","frame":0,"tint":16777215,"anims":{},"behaviours":[{"name":"Acolyte","params":{},"path":"/other/acolyte.js","$$hashKey":"0SV","enabled":true}]},{"type":"LR.Entity.Group","name":"dust","id":242,"x":0,"y":0,"scaleX":1,"scaleY":1,"angle":0,"width":87,"height":48,"visible":true,"alpha":1,"behaviours":[],"children":[{"type":"LR.Entity.Sprite","name":"dust1","id":243,"x":-464.45149999999444,"y":7.358679788586187,"scaleX":1,"scaleY":1,"angle":0,"anchor":{"x":0.5,"y":0.5},"width":48,"height":48,"visible":true,"alpha":1,"key":"enemies-smoke","frame":0,"tint":16777215,"anims":{"blow":{"frames":[0,1,2,3,4,5,6,7],"loop":false,"speed":20}},"behaviours":[]},{"type":"LR.Entity.Sprite","name":"dust2","id":244,"x":-503.45149999999444,"y":7.358679788586187,"scaleX":1,"scaleY":1,"angle":0,"anchor":{"x":0.5,"y":0.5},"width":48,"height":48,"visible":true,"alpha":1,"key":"enemies-smoke","frame":0,"tint":16777215,"anims":{"blow":{"frames":[0,1,2,3,4,5,6,7],"loop":false,"speed":20}},"behaviours":[]}]}]},{"type":"LR.Entity.Group","name":"Komo_FG","id":101,"x":0,"y":0,"scaleX":1,"scaleY":1,"angle":0,"width":383.5078534895812,"height":415.4776445511002,"visible":true,"alpha":1,"behaviours":[],"children":[{"type":"LR.Entity.Group","name":"francis","id":249,"x":0,"y":12,"scaleX":1,"scaleY":1,"angle":0,"width":383.5078534895812,"height":332.7024408462662,"visible":true,"alpha":1,"behaviours":[{"name":"Francis.MainBody","params":{"tail":"#GO_262","stinger":"#GO_268","legs":"#GO_271","eye":"#GO_261","player":"#GO_238","block_wall":"#GO_484","arm":"#GO_250"},"path":"/enemies/francis/main_body.js","$$hashKey":"0CM","enabled":true}],"children":[{"type":"LR.Entity.Group","name":"tail","id":262,"x":240,"y":9,"scaleX":1,"scaleY":1,"angle":0,"width":227.27730272358997,"height":265.25066650636325,"visible":true,"alpha":1,"behaviours":[{"name":"Francis.Tail","params":{"stinger":"#GO_268","mainBody":"#GO_255"},"path":"/enemies/francis/tail.js","$$hashKey":"0CM","enabled":true}],"tweens":{"idle":{"name":"idle","properties":"{\"angle\":-10}","duration":2000,"easing":["Linear","None"],"delay":0,"repeat":-1,"yoyo":true,"relative":true,"autoStart":false},"stunned":{"name":"stunned","properties":"{\"y\":55,\"angle\":-30}","duration":1000,"easing":["Linear","None"],"delay":0,"repeat":0,"yoyo":false,"relative":false,"autoStart":false}},"children":[{"type":"LR.Entity.Sprite","name":"tail5","id":267,"x":-86.76949691772461,"y":-144.7249984741211,"scaleX":1,"scaleY":1,"angle":-57.192355511563036,"anchor":{"x":0.5,"y":0.5},"width":33,"height":49,"visible":true,"alpha":1,"key":"francis-atlas","frame":14,"frameName":"tail5.png","tint":16777215,"anims":{},"behaviours":[],"tweens":{"idle":{"name":"idle","properties":"{\"x\":-24,\"y\":14,\"angle\":-10}","duration":2000,"easing":["Linear","None"],"delay":0,"repeat":-1,"yoyo":true,"relative":true,"autoStart":false},"stunned":{"name":"stunned","properties":"{}","duration":1000,"easing":["Linear","None"],"delay":0,"repeat":0,"yoyo":false,"relative":false,"autoStart":false}}},{"type":"LR.Entity.Sprite","name":"tail4","id":266,"x":-49.76947784423834,"y":-117.72499847412112,"scaleX":1,"scaleY":1,"angle":-54.718221299937625,"anchor":{"x":0.5,"y":0.5},"width":48,"height":72,"visible":true,"alpha":1,"key":"francis-atlas","frame":10,"frameName":"tail_4.png","tint":16777215,"anims":{},"behaviours":[],"tweens":{"idle":{"name":"idle","properties":"{\"x\":-15,\"y\":8,\"angle\":-10}","duration":2000,"easing":["Linear","None"],"delay":0,"repeat":-1,"yoyo":true,"relative":true,"autoStart":false},"stunned":{"name":"stunned","properties":"{}","duration":1000,"easing":["Linear","None"],"delay":0,"repeat":0,"yoyo":false,"relative":false,"autoStart":false}}},{"type":"LR.Entity.Sprite","name":"tail3","id":265,"x":-12.76950454711914,"y":-77.72500038146975,"scaleX":1,"scaleY":1,"angle":-32.005383208083515,"anchor":{"x":0.5,"y":0.5},"width":41,"height":65,"visible":true,"alpha":1,"key":"francis-atlas","frame":12,"frameName":"tail3.png","tint":16777215,"anims":{},"behaviours":[],"tweens":{"idle":{"name":"idle","properties":"{\"x\":-11,\"y\":8,\"angle\":-8}","duration":2000,"easing":["Linear","None"],"delay":0,"repeat":-1,"yoyo":true,"relative":true,"autoStart":false},"stunned":{"name":"stunned","properties":"{}","duration":1000,"easing":["Linear","None"],"delay":0,"repeat":0,"yoyo":false,"relative":false,"autoStart":false}}},{"type":"LR.Entity.Sprite","name":"tail2","id":264,"x":10.230491638183594,"y":-30.725000619888306,"scaleX":1,"scaleY":1,"angle":-20.62276997730129,"anchor":{"x":0.5,"y":0.5},"width":42,"height":66,"visible":true,"alpha":1,"key":"francis-atlas","frame":11,"frameName":"tail2.png","tint":16777215,"anims":{},"behaviours":[],"tweens":{"idle":{"name":"idle","properties":"{\"angle\":-10,\"x\":-5}","duration":2000,"easing":["Linear","None"],"delay":0,"repeat":-1,"yoyo":true,"relative":true,"autoStart":false},"stunned":{"name":"stunned","properties":"{}","duration":1000,"easing":["Linear","None"],"delay":0,"repeat":0,"yoyo":false,"relative":false,"autoStart":false}}},{"type":"LR.Entity.Sprite","name":"tail1","id":263,"x":0,"y":7,"scaleX":1,"scaleY":1,"angle":46.02564002631584,"anchor":{"x":0.5,"y":0.5},"width":42,"height":66,"visible":true,"alpha":1,"key":"francis-atlas","frame":11,"frameName":"tail2.png","tint":16777215,"anims":{},"behaviours":[],"tweens":{"idle":{"name":"idle","properties":"{\"angle\":-5,\"x\":-5}","duration":2000,"easing":["Linear","None"],"delay":0,"repeat":-1,"yoyo":true,"relative":true,"autoStart":false},"stunned":{"name":"stunned","properties":"{}","duration":1000,"easing":["Linear","None"],"delay":0,"repeat":0,"yoyo":false,"relative":false,"autoStart":false}}},{"type":"LR.Entity.Group","name":"stinger","id":268,"x":0,"y":0,"scaleX":1,"scaleY":1,"angle":0,"width":103.99994659423828,"height":79,"visible":true,"alpha":1,"behaviours":[{"name":"Francis.Stinger","params":{"orb":"#GO_270","stinger":"#GO_269"},"path":"/enemies/francis/stinger.js","$$hashKey":"0CU","enabled":true}],"tweens":{"idle":{"name":"idle","properties":"{\"y\":4,\"x\":-5,\"angle\":-10}","duration":2000,"easing":["Linear","None"],"delay":0,"repeat":-1,"yoyo":true,"relative":true,"autoStart":false},"stunned":{"name":"stunned","properties":"{}","duration":1000,"easing":["Linear","None"],"delay":0,"repeat":0,"yoyo":false,"relative":false,"autoStart":false}},"children":[{"type":"LR.Entity.Sprite","name":"stinger","id":269,"x":-134.7694492340088,"y":-180.72490310668945,"scaleX":1,"scaleY":1,"angle":0,"anchor":{"x":0.5,"y":0.5},"width":102,"height":79,"visible":true,"alpha":1,"key":"francis-atlas","frame":1,"frameName":"tail_hook.png","tint":16777215,"anims":{},"layer":"default","body":{"motion":"DYNAMIC","enabled":true,"fixedRotation":true,"angle":0,"gravity":0,"mass":1,"bindRotation":false,"debug":false,"shapes":[{"x":7.000000000000002,"y":-25,"width":99,"height":76,"rotation":0,"sensor":true,"name":"mainShape","type":"rectangle"}]},"behaviours":[]},{"type":"LR.Entity.Sprite","name":"orb","id":270,"x":-113.76950263977051,"y":-184.72491836547852,"scaleX":1,"scaleY":1,"angle":0,"anchor":{"x":0.5,"y":0.5},"width":64,"height":64,"visible":true,"alpha":1,"key":"francis-atlas","frame":7,"frameName":"orb.png","tint":16777215,"anims":{},"layer":"default","body":{"motion":"DYNAMIC","enabled":true,"angle":0,"gravity":0,"mass":1,"bindRotation":false,"debug":false,"shapes":[{"x":0,"y":0,"width":52,"height":50,"rotation":0,"sensor":true,"name":"mainShape","type":"rectangle"}]},"behaviours":[]}]}]},{"type":"LR.Entity.Group","name":"body","id":255,"x":4,"y":0,"scaleX":1,"scaleY":1,"angle":0,"width":237,"height":82.49982833862305,"visible":true,"alpha":1,"behaviours":[],"tweens":{"idle":{"name":"idle","properties":"{\"y\":5}","duration":2000,"easing":["Linear","None"],"delay":0,"repeat":-1,"yoyo":true,"relative":true,"autoStart":true},"stunned":{"name":"stunned","properties":"{\"y\":\"55\"}","duration":1000,"easing":["Linear","None"],"delay":0,"repeat":0,"yoyo":false,"relative":false,"autoStart":false}},"children":[{"type":"LR.Entity.Sprite","name":"body2","id":259,"x":203,"y":19,"scaleX":1,"scaleY":1,"angle":0,"anchor":{"x":0.5,"y":0.5},"width":74,"height":67,"visible":true,"alpha":1,"key":"francis-atlas","frame":4,"frameName":"body2.png","tint":16777215,"anims":{},"behaviours":[]},{"type":"LR.Entity.Sprite","name":"body1","id":258,"x":154,"y":24,"scaleX":1,"scaleY":1,"angle":0,"anchor":{"x":0.5,"y":0.5},"width":71,"height":82,"visible":true,"alpha":1,"key":"francis-atlas","frame":5,"frameName":"body1.png","tint":16777215,"anims":{},"behaviours":[]},{"type":"LR.Entity.Sprite","name":"pincer_back","id":260,"x":44,"y":15,"scaleX":1,"scaleY":1,"angle":0,"anchor":{"x":0.5,"y":0.5},"width":82,"height":55,"visible":true,"alpha":1,"key":"francis-atlas","frame":3,"frameName":"pincher_little.png","tint":16777215,"anims":{},"behaviours":[],"tweens":{"idle":{"name":"idle","properties":"{\"angle\":8}","duration":1000,"easing":["Linear","None"],"delay":0,"repeat":-1,"yoyo":true,"relative":true,"autoStart":true}}},{"type":"LR.Entity.Sprite","name":"head","id":257,"x":98.99994468688965,"y":23.000171661376953,"scaleX":1,"scaleY":1,"angle":0,"anchor":{"x":0.5,"y":0.5},"width":92,"height":81,"visible":true,"alpha":1,"key":"francis-atlas","frame":2,"frameName":"head.png","tint":16777215,"anims":{},"layer":"ground","body":{"motion":"DYNAMIC","enabled":true,"angle":0,"gravity":0,"mass":1,"bindRotation":false,"debug":false,"shapes":[{"x":0,"y":0,"width":92.00000000000001,"height":81,"rotation":0,"sensor":true,"name":"headShape","type":"rectangle"}]},"behaviours":[{"name":"LR.Behaviour.Trigger","params":{"callbackName":"onHitByRock","messageObject":{},"otherNotified":"#GO_249","activeCountLimit":0},"desc":null,"path":"/common/trigger.js","enabled":true,"$$hashKey":"0O5"}]},{"type":"LR.Entity.Sprite","name":"eye","id":261,"x":93,"y":20,"scaleX":0.9375000000000001,"scaleY":0.9375,"angle":0,"anchor":{"x":0.5,"y":0.5},"width":60.00000000000001,"height":60,"visible":true,"alpha":1,"key":"enemies-francis-eye","frame":0,"tint":16777215,"anims":{"blink":{"frames":[0,1,2,1,0],"loop":false,"speed":16,"timer":6},"stunned":{"frames":[3],"loop":false,"speed":60}},"autoPlayAnim":"blink","behaviours":[]}]},{"type":"LR.Entity.Group","name":"arm","id":250,"x":124,"y":39,"scaleX":1,"scaleY":1,"angle":0,"width":238,"height":97,"visible":true,"alpha":1,"behaviours":[{"name":"Francis.Arm","params":{"boulders":"#GO_490","boulderMe":"#GO_515"},"path":"/enemies/francis/arm.js","$$hashKey":"0CG","enabled":true}],"tweens":{"idle":{"name":"idle","properties":"{\"angle\":-5}","duration":2000,"easing":["Linear","None"],"delay":382,"repeat":-1,"yoyo":true,"relative":true,"autoStart":true},"ready":{"name":"ready","properties":"{\"angle\":30}","duration":2000,"easing":["Exponential","In"],"delay":0,"repeat":0,"yoyo":false,"relative":false,"autoStart":false},"stomp":{"name":"stomp","properties":"{\"angle\":-5}","duration":100,"easing":["Linear","None"],"delay":500,"repeat":0,"yoyo":false,"relative":false,"autoStart":false},"ready_quick":{"name":"ready_quick","properties":"{\"angle\":30}","duration":1500,"easing":["Linear","None"],"delay":0,"repeat":0,"yoyo":false,"relative":false,"autoStart":false},"stunned":{"name":"stunned","properties":"{\"y\":100,\"angle\":-15}","duration":1000,"easing":["Linear","None"],"delay":0,"repeat":0,"yoyo":false,"relative":false,"autoStart":false}},"sounds":[{"name":"stomp","key":"fx-stomp.wav","autoPlay":false,"loop":true,"volume":1,"is3D":false,"volumeMax3D":1,"distance3D":300,"$$hashKey":"0LF"}],"children":[{"type":"LR.Entity.Sprite","name":"arm3","id":252,"x":1,"y":1,"scaleX":1,"scaleY":1,"angle":0,"anchor":{"x":0.5,"y":0.5},"width":22,"height":22,"visible":true,"alpha":1,"key":"francis-atlas","frame":19,"frameName":"arm_0.png","tint":16777215,"anims":{},"behaviours":[]},{"type":"LR.Entity.Sprite","name":"arm2","id":251,"x":-23,"y":14,"scaleX":1,"scaleY":1,"angle":0,"anchor":{"x":0.5,"y":0.5},"width":49,"height":43,"visible":true,"alpha":1,"key":"francis-atlas","frame":9,"frameName":"arm_1.png","tint":16777215,"anims":{},"behaviours":[]},{"type":"LR.Entity.Sprite","name":"arm1","id":247,"x":-55,"y":33,"scaleX":1,"scaleY":1,"angle":0,"anchor":{"x":0.5,"y":0.5},"width":64,"height":64,"visible":true,"alpha":1,"key":"francis-atlas","frame":6,"frameName":"arm_2.png","tint":16777215,"anims":{},"behaviours":[]},{"type":"LR.Entity.Group","name":"pincer","id":284,"x":-98,"y":23,"scaleX":1,"scaleY":1,"angle":0,"width":162,"height":97,"visible":true,"alpha":1,"behaviours":[],"children":[{"type":"LR.Entity.Sprite","name":"pincer","id":254,"x":-47,"y":0,"scaleX":1,"scaleY":1,"angle":0,"anchor":{"x":0.5,"y":0.5},"width":162,"height":95,"visible":true,"alpha":1,"key":"francis-atlas","frame":0,"frameName":"pincher_big.png","tint":16777215,"anims":{},"behaviours":[],"tweens":{"idle":{"name":"idle","properties":"{\"angle\":3}","duration":1500,"easing":["Linear","None"],"delay":0,"repeat":-1,"yoyo":true,"relative":true,"autoStart":true}}},{"type":"LR.Entity.Sprite","name":"little_pincer","id":253,"x":-39,"y":-29,"scaleX":1,"scaleY":1,"angle":0,"anchor":{"x":0.5,"y":0.5},"width":60,"height":41,"visible":true,"alpha":1,"key":"francis-atlas","frame":8,"frameName":"pincher_thumb.png","tint":16777215,"anims":{},"behaviours":[],"tweens":{"clap":{"name":"clap","properties":"{\"angle\":-45,\"x\":5,\"y\":8}","duration":300,"easing":["Linear","None"],"delay":0,"repeat":2,"yoyo":true,"relative":true,"autoStart":true,"chain":"idle"},"idle":{"name":"idle","properties":"{\"angle\":5}","duration":1000,"easing":["Linear","None"],"delay":0,"repeat":0,"yoyo":true,"relative":true,"autoStart":false,"chain":"clap"}}}]}]},{"type":"LR.Entity.Group","name":"legs","id":271,"x":178,"y":60,"scaleX":1,"scaleY":1,"angle":0,"width":113.64600068863705,"height":90.46977210285861,"visible":true,"alpha":1,"behaviours":[{"name":"Francis.Legs","params":{},"desc":null,"path":"/enemies/francis/legs.js","enabled":true,"$$hashKey":"0J5"}],"children":[{"type":"LR.Entity.Group","name":"leg1","id":273,"x":-41,"y":0,"scaleX":1,"scaleY":1,"angle":0,"width":39.35718273417633,"height":90.46977210285861,"visible":true,"alpha":1,"behaviours":[{"name":"Francis.Leg","params":{"part1":"#GO_272","part2":"#GO_274"},"desc":null,"path":"/enemies/francis/leg.js","enabled":true,"$$hashKey":"2KL"}],"children":[{"type":"LR.Entity.Sprite","name":"part1","id":272,"x":0,"y":0,"scaleX":1,"scaleY":1,"angle":16.939085631049494,"anchor":{"x":0.5,"y":0.5},"width":25,"height":53,"visible":true,"alpha":1,"key":"francis-atlas","frame":15,"frameName":"leg1_top.png","tint":16777215,"anims":{},"behaviours":[],"tweens":{"walk":{"name":"walk","properties":"{\"angle\":10,\"y\":-2,\"x\":-1}","duration":1000,"easing":["Linear","None"],"delay":0,"repeat":0,"yoyo":false,"relative":true,"autoStart":false,"chain":"walk2"},"walk2":{"name":"walk2","properties":"{\"y\":2}","duration":1000,"easing":["Linear","None"],"delay":0,"repeat":0,"yoyo":false,"relative":true,"autoStart":false,"chain":"walk3"},"walk3":{"name":"walk3","properties":"{\"angle\":-10,\"x\":1}","duration":1000,"easing":["Linear","None"],"delay":0,"repeat":0,"yoyo":false,"relative":true,"autoStart":false,"chain":"walk"},"idle":{"name":"idle","properties":"{\"y\":1,\"scale.y\":-0.1}","duration":2000,"easing":["Linear","None"],"delay":0,"repeat":-1,"yoyo":true,"relative":true,"autoStart":true},"stunned":{"name":"stunned","properties":"{\"scale.y\":0,\"y\":40,\"x\":15,\"angle\":50}","duration":1000,"easing":["Linear","None"],"delay":0,"repeat":0,"yoyo":false,"relative":false,"autoStart":false}}},{"type":"LR.Entity.Sprite","name":"part2","id":274,"x":-2,"y":36,"scaleX":1,"scaleY":1,"angle":-11.96766287104515,"anchor":{"x":0.5,"y":0.5},"width":24,"height":47,"visible":true,"alpha":1,"key":"francis-atlas","frame":17,"frameName":"leg1_bottom.png","tint":16777215,"anims":{},"behaviours":[],"tweens":{"walk":{"name":"walk","properties":"{\"x\":-3,\"y\":-3}","duration":1000,"easing":["Linear","None"],"delay":0,"repeat":0,"yoyo":false,"relative":true,"autoStart":false,"chain":"walk2"},"walk2":{"name":"walk2","properties":"{\"x\":-1,\"y\":3}","duration":1000,"easing":["Linear","None"],"delay":0,"repeat":0,"yoyo":false,"relative":true,"autoStart":false,"chain":"walk3"},"walk3":{"name":"walk3","properties":"{\"x\":4}","duration":1000,"easing":["Linear","None"],"delay":0,"repeat":0,"yoyo":false,"relative":true,"autoStart":false,"chain":"walk"},"stunned":{"name":"stunned","properties":"{\"angle\":50,\"y\":50}","duration":1000,"easing":["Linear","None"],"delay":0,"repeat":0,"yoyo":false,"relative":false,"autoStart":false}}}]},{"type":"LR.Entity.Group","name":"leg2","id":275,"x":-17,"y":0,"scaleX":1,"scaleY":1,"angle":0,"width":33.781625665506205,"height":83.02573207609657,"visible":true,"alpha":1,"behaviours":[{"name":"Francis.Leg","params":{"part1":"#GO_276","part2":"#GO_277"},"desc":null,"path":"/enemies/francis/leg.js","enabled":true,"$$hashKey":"1XH"}],"children":[{"type":"LR.Entity.Sprite","name":"part1","id":276,"x":0,"y":-0.3415,"scaleX":1,"scaleY":0.8404000000000238,"angle":5.136572634506962,"anchor":{"x":0.5,"y":0.5},"width":25,"height":44.54120000000126,"visible":true,"alpha":1,"key":"francis-atlas","frame":15,"frameName":"leg1_top.png","tint":16777215,"anims":{},"behaviours":[],"tweens":{"idle":{"name":"idle","properties":"{\"y\":1,\"scale.y\":-0.1}","duration":2000,"easing":["Linear","None"],"delay":0,"repeat":1.7976931348623157e+308,"yoyo":true,"relative":true,"autoStart":true},"stunned":{"name":"stunned","properties":"{\"scale.y\":0,\"y\":25,\"x\":5}","duration":1000,"easing":["Linear","None"],"delay":0,"repeat":0,"yoyo":false,"relative":false,"autoStart":false}}},{"type":"LR.Entity.Sprite","name":"part2","id":277,"x":3,"y":34,"scaleX":1,"scaleY":1,"angle":-11.205438422322175,"anchor":{"x":0.5,"y":0.5},"width":24,"height":47,"visible":true,"alpha":1,"key":"francis-atlas","frame":17,"frameName":"leg1_bottom.png","tint":16777215,"anims":{},"behaviours":[],"tweens":{"stunned":{"name":"stunned","properties":"{\"scale.y\":0.9,\"y\":40,\"x\":2,\"angle\":15}","duration":1000,"easing":["Linear","None"],"delay":0,"repeat":0,"yoyo":false,"relative":false,"autoStart":false}}}]},{"type":"LR.Entity.Group","name":"leg3","id":278,"x":8,"y":0,"scaleX":1,"scaleY":1,"angle":0,"width":35.27639402523654,"height":83.4119229025525,"visible":true,"alpha":1,"behaviours":[{"name":"Francis.Leg","params":{"part1":"#GO_279","part2":"#GO_280"},"desc":null,"path":"/enemies/francis/leg.js","enabled":true,"$$hashKey":"1A8"}],"children":[{"type":"LR.Entity.Sprite","name":"part1","id":279,"x":0,"y":-1.05,"scaleX":1,"scaleY":0.8112500000014999,"angle":-15,"anchor":{"x":0.5,"y":0.5},"width":25,"height":42.9962500000795,"visible":true,"alpha":1,"key":"francis-atlas","frame":16,"frameName":"leg2_top.png","tint":16777215,"anims":{},"behaviours":[],"tweens":{"idle":{"name":"idle","properties":"{\"y\":1,\"scale.y\":-0.1}","duration":2000,"easing":["Linear","None"],"delay":0,"repeat":1.7976931348623157e+308,"yoyo":true,"relative":true,"autoStart":true},"stunned":{"name":"stunned","properties":"{\"scale.y\":0,\"y\":25,\"angle\":-30,\"x\":-2}","duration":1000,"easing":["Linear","None"],"delay":0,"repeat":0,"yoyo":false,"relative":false,"autoStart":false}}},{"type":"LR.Entity.Sprite","name":"part2","id":280,"x":3,"y":34,"scaleX":1,"scaleY":1,"angle":4.454883154522236,"anchor":{"x":0.5,"y":0.5},"width":24,"height":47,"visible":true,"alpha":1,"key":"francis-atlas","frame":18,"frameName":"leg2_bottom.png","tint":16777215,"anims":{},"behaviours":[],"tweens":{"stunned":{"name":"stunned","properties":"{\"scale.y\":0.9,\"y\":40,\"x\":10,\"angle\":-20}","duration":1000,"easing":["Linear","None"],"delay":0,"repeat":0,"yoyo":false,"relative":false,"autoStart":false}}}]},{"type":"LR.Entity.Group","name":"leg4","id":281,"x":32,"y":0,"scaleX":1,"scaleY":1,"angle":0,"width":41.93481864309777,"height":87.83948446543657,"visible":true,"alpha":1,"behaviours":[{"name":"Francis.Leg","params":{"part1":"#GO_282","part2":"#GO_283"},"desc":null,"path":"/enemies/francis/leg.js","enabled":true,"$$hashKey":"0N4"}],"children":[{"type":"LR.Entity.Sprite","name":"part1","id":282,"x":0,"y":0.5535,"scaleX":1,"scaleY":0.94465,"angle":-22,"anchor":{"x":0.5,"y":0.5},"width":25,"height":50.066449999999996,"visible":true,"alpha":1,"key":"francis-atlas","frame":16,"frameName":"leg2_top.png","tint":16777215,"anims":{},"behaviours":[],"tweens":{"idle":{"name":"idle","properties":"{\"y\":1,\"scale.y\":-0.1}","duration":2000,"easing":["Linear","None"],"delay":0,"repeat":1.7976931348623157e+308,"yoyo":true,"relative":true,"autoStart":true},"stunned":{"name":"stunned","properties":"{\"scale.y\":0.01,\"y\":30,\"angle\":-40,\"x\":5}","duration":1000,"easing":["Linear","None"],"delay":0,"repeat":0,"yoyo":false,"relative":false,"autoStart":false}}},{"type":"LR.Entity.Sprite","name":"part2","id":283,"x":7,"y":37,"scaleX":1,"scaleY":1,"angle":0,"anchor":{"x":0.5,"y":0.5},"width":24,"height":47,"visible":true,"alpha":1,"key":"francis-atlas","frame":18,"frameName":"leg2_bottom.png","tint":16777215,"anims":{},"behaviours":[],"tweens":{"stunned":{"name":"stunned","properties":"{\"y\":40,\"angle\":-50,\"x\":20}","duration":1000,"easing":["Linear","None"],"delay":0,"repeat":0,"yoyo":false,"relative":false,"autoStart":false}}}]}]}]},{"type":"LR.Entity.Group","name":"falling_rock_me","id":514,"x":105,"y":-218,"scaleX":1,"scaleY":1,"angle":0,"width":128,"height":128,"visible":true,"alpha":1,"behaviours":[],"children":[{"type":"LR.Entity.Sprite","name":"rock_me","id":515,"x":-0.0000858306884765625,"y":-0.0001068115234375,"scaleX":2,"scaleY":2,"angle":0,"anchor":{"x":0.5,"y":0.5},"width":128,"height":128,"visible":true,"alpha":1,"key":"stone-atlas_stone_1","frame":1,"frameName":"rock.png","tint":16777215,"anims":{},"layer":"enemy","body":{"motion":"DYNAMIC","enabled":true,"angle":0,"gravity":0,"mass":1,"bindRotation":false,"debug":false,"shapes":[{"x":0,"y":0,"radius":23.000000000000004,"rotation":0,"sensor":true,"name":"mainShape","type":"circle"}]},"behaviours":[{"name":"FallingObject","params":{"direction":1,"hatable":true,"dead":false,"smoke":"#GO_516","repeatTime":-1},"desc":null,"path":"/enemies/falling_object.js","enabled":true,"$$hashKey":"1ZT"}],"sounds":[{"name":"death","key":"fx-rock_explode.wav","autoPlay":false,"loop":true,"volume":1,"is3D":false,"volumeMax3D":1,"distance3D":300,"$$hashKey":"0JW"}]},{"type":"LR.Entity.Sprite","name":"smoke","id":516,"x":0,"y":-4,"scaleX":2,"scaleY":2,"angle":0,"anchor":{"x":0.5,"y":0.5},"width":96,"height":96,"visible":true,"alpha":1,"outOfViewHide":true,"key":"enemies-smoke","frame":0,"tint":16777215,"anims":{"blow":{"frames":[0,1,2,3,4,5,6,7],"loop":false,"speed":20}},"behaviours":[],"sounds":[{"name":"blow","key":"fx-smoke.wav","autoPlay":false,"loop":true,"volume":1,"is3D":false,"volumeMax3D":1,"distance3D":300,"$$hashKey":"0L5"}]}]}]},{"type":"LR.Entity.Group","name":"decor_FG","id":102,"x":0,"y":0,"scaleX":1,"scaleY":1,"angle":0,"width":0,"height":0,"visible":true,"alpha":1,"behaviours":[]},{"type":"LR.Entity.Group","name":"UI_InGame","id":225,"x":0,"y":0,"scaleX":1,"scaleY":1,"angle":0,"width":732.3269513850069,"height":176.53529489086623,"prefab":{"name":"UI_InGame","path":"/UI_InGame.json"},"visible":true,"alpha":1,"behaviours":[{"name":"UIInGame","params":{"coins":"#GO_286","lives":"#GO_285","quit_button":"#GO_473","mute_button":"#GO_472"},"path":"/ui/ui_ingame.js","$$hashKey":"0A5","enabled":true}],"children":[{"type":"LR.Entity.Group","name":"Coins","id":226,"x":599,"y":26,"scaleX":0.6,"scaleY":0.6,"angle":0,"width":73.5,"height":28.799999999999997,"visible":true,"alpha":1,"fixedToCamera":true,"behaviours":[],"children":[{"type":"LR.Entity.Sprite","name":"sprite_coin","id":229,"x":-46,"y":0,"scaleX":1.5,"scaleY":1.5,"angle":0,"anchor":{"x":0.5,"y":0.5},"width":48,"height":48,"visible":true,"alpha":1,"key":"items-egg","frame":0,"tint":16777215,"anims":{},"behaviours":[]},{"type":"LR.Entity.BitmapText","name":"txt_coins","id":286,"x":-14,"y":-43,"scaleX":1,"scaleY":1,"angle":0,"textData":{"text":"00","fontSize":76,"font":"brady_bunch"},"visible":true,"alpha":1,"tint":16777215,"behaviours":[],"children":[]}]},{"type":"LR.Entity.Group","name":"Lives","id":230,"x":53,"y":26,"scaleX":0.6,"scaleY":0.6,"angle":0,"width":80.1,"height":32.4,"visible":true,"alpha":1,"fixedToCamera":true,"behaviours":[],"children":[{"type":"LR.Entity.Sprite","name":"sprite_life","id":233,"x":-55,"y":0,"scaleX":1.625,"scaleY":1.6875,"angle":0,"anchor":{"x":0.5,"y":0.5},"width":52,"height":54,"visible":true,"alpha":1,"key":"items-life","frame":3,"tint":16777215,"anims":{},"behaviours":[]},{"type":"LR.Entity.BitmapText","name":"txt_lives","id":285,"x":-14,"y":-40,"scaleX":1,"scaleY":1,"angle":0,"textData":{"text":"00","fontSize":76,"font":"brady_bunch"},"visible":true,"alpha":1,"tint":16777215,"behaviours":[],"children":[]}]},{"type":"LR.Entity.Group","name":"input_tactile","id":234,"x":-100,"y":31,"scaleX":1,"scaleY":1,"angle":0,"width":0,"height":0,"prefab":{"name":"input_tactile","path":"/input_tactile.json"},"visible":true,"alpha":1,"behaviours":[{"name":"InputTactile","params":{"leftName":"left_button","rightName":"right_button","player":"#GO_238"},"path":"/ui/input_tactile.js","$$hashKey":"06Q","enabled":true}],"children":[{"type":"LR.Entity.Button","name":"left_button","id":235,"x":136,"y":285,"scaleX":0.5,"scaleY":1.28125,"angle":0,"anchor":{"x":0.5,"y":0.5},"width":32,"height":82,"visible":false,"alpha":0.3,"key":"ui-dir_button","frame":0,"fixedToCamera":true,"onOverFrameID":0,"onOutFrameID":0,"onDownFrameID":0,"onUpFrameID":0,"tint":16777215,"anims":{},"behaviours":[{"name":"DirectionButton","params":{"direction":"left"},"path":"/ui/direction_button.js","$$hashKey":"06V","enabled":true}]},{"type":"LR.Entity.Button","name":"right_button","id":236,"x":208,"y":285,"scaleX":-1,"scaleY":1,"angle":0,"anchor":{"x":0.5,"y":0.5},"width":-64,"height":64,"visible":false,"alpha":0.3,"key":"ui-dir_button","frame":0,"fixedToCamera":true,"onOverFrameID":0,"onOutFrameID":0,"onDownFrameID":0,"onUpFrameID":0,"tint":16777215,"anims":{},"behaviours":[{"name":"DirectionButton","params":{"direction":"right"},"path":"/ui/direction_button.js","$$hashKey":"06V","enabled":true}]}]},{"type":"LR.Entity.Group","name":"menu","id":470,"x":0,"y":0,"scaleX":1,"scaleY":1,"angle":0,"width":732.3269513850069,"height":37.07058978173245,"visible":true,"alpha":1,"behaviours":[],"children":[{"type":"LR.Entity.Button","name":"quit_button","id":473,"x":-30,"y":24,"scaleX":1,"scaleY":1,"angle":0,"anchor":{"x":0.5,"y":0.5},"width":32,"height":32,"visible":true,"alpha":1,"key":"ui-ingame_buttons_32x32","frame":2,"fixedToCamera":true,"onOverFrameID":2,"onOutFrameID":2,"onDownFrameID":2,"onUpFrameID":2,"tint":16777215,"anims":{},"behaviours":[{"name":"QuitButton","params":{},"desc":null,"path":"/ui/quit_button.js","$$hashKey":"0RV","enabled":true}]},{"type":"LR.Entity.Button","name":"mute_button","id":472,"x":667.7916564941406,"y":22,"scaleX":1,"scaleY":1,"angle":10,"anchor":{"x":0.5,"y":0.5},"width":32,"height":32,"visible":true,"alpha":1,"key":"ui-ingame_buttons_32x32","frame":0,"fixedToCamera":true,"onOverFrameID":0,"onOutFrameID":0,"onDownFrameID":0,"onUpFrameID":0,"tint":16777215,"anims":{},"behaviours":[{"name":"MuteButton","params":{},"desc":null,"path":"/ui/mute_button.js","$$hashKey":"0MT","enabled":true}]}]}]},{"type":"LR.Entity.Sprite","name":"trigger_intro","id":482,"x":-293.0000305175781,"y":77.99999713897705,"scaleX":1,"scaleY":4.747919261594799,"angle":0,"anchor":{"x":0.5,"y":0.5},"width":32,"height":151.93341637103356,"visible":true,"alpha":1,"tint":16777215,"anims":{},"layer":"default","body":{"motion":"STATIC","enabled":true,"angle":0,"gravity":1,"mass":1.7976931348623157e+308,"bindRotation":false,"debug":false,"shapes":[{"x":0,"y":0,"width":32,"height":151.93341637103356,"rotation":0,"sensor":true,"name":"mainShape","type":"rectangle"}]},"behaviours":[{"name":"LR.Behaviour.Trigger","params":{"callbackName":"launchIntro","messageObject":{},"otherNotified":"#GO_249","activeCountLimit":1,"interactives":["player"]},"desc":null,"path":"/common/trigger.js","enabled":true,"$$hashKey":"0GZ"}]}]},"settings":{"camera":{"x":-320,"y":-180,"width":640,"height":360,"debug":true,"fixedToCamera":true},"debugBodiesInGame":true,"ed_camera":{"x":-211.66250024414063,"y":-342.0960000305176}}}